pyramid_flower/__init__.py
pyramid_flower/script.py
pyramid_flower-0.0.2.dist-info/LICENSE
pyramid_flower-0.0.2.dist-info/METADATA
pyramid_flower-0.0.2.dist-info/WHEEL
pyramid_flower-0.0.2.dist-info/entry_points.txt
pyramid_flower-0.0.2.dist-info/RECORD
