Metadata-Version: 2.1
Name: pyramid_flower
Version: 0.0.2
Summary: Just a celery command to start flower with pyramid celery
Home-page: https://github.com/tomascorrea/pyramid-flower
Author: Tomás Corrêa
Author-email: tomas.correa@gmail.com
Requires-Python: >=3.8,<4.0
Classifier: Programming Language :: Python :: 3
Classifier: Programming Language :: Python :: 3.8
Classifier: Programming Language :: Python :: 3.9
Classifier: Programming Language :: Python :: 3.10
Classifier: Programming Language :: Python :: 3.11
Classifier: Programming Language :: Python :: 3.12
Requires-Dist: celery (>=5.4.0,<6.0.0)
Requires-Dist: click (>=8.1.8,<9.0.0)
Requires-Dist: flower (>=2.0.1,<3.0.0)
Requires-Dist: pyramid (>=2.0.2,<3.0.0)
Requires-Dist: pyramid-celery (>=4.0.0,<5.0.0)
Requires-Dist: tornado (>=6.4.2,<7.0.0)
Project-URL: Documentation, https://tomascorrea.github.io/pyramid-flower/
Project-URL: Repository, https://github.com/tomascorrea/pyramid-flower
